pybraflog/__init__.py
pybraflog/flog.py
pybraflog-0.1.3.dist-info/LICENSE
pybraflog-0.1.3.dist-info/METADATA
pybraflog-0.1.3.dist-info/WHEEL
pybraflog-0.1.3.dist-info/RECORD
